odoo/addons/l10n_eu_product_adr_dangerous_goods/README.rst
odoo/addons/l10n_eu_product_adr_dangerous_goods/__init__.py
odoo/addons/l10n_eu_product_adr_dangerous_goods/__manifest__.py
odoo/addons/l10n_eu_product_adr_dangerous_goods/data/utility_models.xml
odoo/addons/l10n_eu_product_adr_dangerous_goods/i18n/es.po
odoo/addons/l10n_eu_product_adr_dangerous_goods/i18n/fr.po
odoo/addons/l10n_eu_product_adr_dangerous_goods/i18n/it.po
odoo/addons/l10n_eu_product_adr_dangerous_goods/i18n/l10n_eu_product_adr_dangerous_goods.pot
odoo/addons/l10n_eu_product_adr_dangerous_goods/models/__init__.py
odoo/addons/l10n_eu_product_adr_dangerous_goods/models/product_product.py
odoo/addons/l10n_eu_product_adr_dangerous_goods/models/utility_models.py
odoo/addons/l10n_eu_product_adr_dangerous_goods/readme/CONTRIBUTORS.md
odoo/addons/l10n_eu_product_adr_dangerous_goods/readme/CREDITS.md
odoo/addons/l10n_eu_product_adr_dangerous_goods/readme/DESCRIPTION.md
odoo/addons/l10n_eu_product_adr_dangerous_goods/readme/ROADMAP.md
odoo/addons/l10n_eu_product_adr_dangerous_goods/security/ir.model.access.csv
odoo/addons/l10n_eu_product_adr_dangerous_goods/static/description/icon.png
odoo/addons/l10n_eu_product_adr_dangerous_goods/static/description/index.html
odoo/addons/l10n_eu_product_adr_dangerous_goods/tests/__init__.py
odoo/addons/l10n_eu_product_adr_dangerous_goods/tests/test_product_product.py
odoo/addons/l10n_eu_product_adr_dangerous_goods/views/product_product.xml
odoo_addon_l10n_eu_product_adr_dangerous_goods-18.0.1.0.0.7.dist-info/METADATA
odoo_addon_l10n_eu_product_adr_dangerous_goods-18.0.1.0.0.7.dist-info/WHEEL
odoo_addon_l10n_eu_product_adr_dangerous_goods-18.0.1.0.0.7.dist-info/top_level.txt
odoo_addon_l10n_eu_product_adr_dangerous_goods-18.0.1.0.0.7.dist-info/RECORD
