Metadata-Version: 2.1
Name: odoo-addon-l10n_eu_product_adr_dangerous_goods
Version: 18.0.1.0.0.7
Requires-Python: >=3.10
Requires-Dist: odoo-addon-l10n_eu_product_adr==18.0.*
Requires-Dist: odoo==18.0.*
Summary: l10n Eu Product Adr Dangerous Goods
Home-page: https://github.com/OCA/community-data-files
License: AGPL-3
Author: Camptocamp, Odoo Community Association (OCA)
Author-email: support@odoo-community.org
Classifier: Programming Language :: Python
Classifier: Framework :: Odoo
Classifier: Framework :: Odoo :: 18.0
Classifier: License :: OSI Approved :: GNU Affero General Public License v3
